setup.py
dockerpty/__init__.py
dockerpty/io.py
dockerpty/pty.py
dockerpty/tty.py
dockerpty.egg-info/PKG-INFO
dockerpty.egg-info/SOURCES.txt
dockerpty.egg-info/dependency_links.txt
dockerpty.egg-info/top_level.txt